LICENSE
MANIFEST.in
README.rst
dreq.xml
dreq2Defn.xml
requirements.txt
runtests.sh
setup.cfg
setup.py
dreq/__init__.py
dreq/_initializer.py
dreq/_utils.py
dreq/constants.py
dreq/options.py
dreq.egg-info/PKG-INFO
dreq.egg-info/SOURCES.txt
dreq.egg-info/dependency_links.txt
dreq.egg-info/not-zip-safe
dreq.egg-info/top_level.txt
dreq/config/__init__.py
dreq/config/initializer.py
dreq/config/table.py
dreq/config/table_attribute.py
dreq/config/wrapper.py
dreq/config/xml_parser.py
dreq/content/__init__.py
dreq/content/initializer.py
dreq/content/query.py
dreq/content/section.py
dreq/content/section_item.py
dreq/content/wrapper.py
dreq/content/xml_parser.py
tests/__init__.py
tests/test_config.py
tests/test_config_table.py
tests/test_config_table_attribute.py
tests/test_content.py
tests/test_content_section.py
tests/test_content_section_item.py